{
  "manifest_version": "1.0",
  "generated_at": "2026-02-13T14:17:00Z",
  "generated_by": "aria_work_cycle",
  "critical_configs": [
    {
      "name": "Environment Configuration",
      "path": "/root/.openclaw/workspace/.env",
      "backup_location": "aria_memories/exports/env_backup.json",
      "priority": "critical",
      "last_verified": null
    },
    {
      "name": "Gateway Configuration",
      "path": "/root/.openclaw/workspace/gateway.yaml",
      "backup_location": "aria_memories/exports/gateway_backup.yaml",
      "priority": "critical",
      "last_verified": null
    },
    {
      "name": "Cron Jobs Schedule",
      "path": "/root/.openclaw/workspace/cron_jobs.yaml",
      "backup_location": "aria_memories/exports/cron_jobs_backup.yaml",
      "priority": "high",
      "last_verified": null
    },
    {
      "name": "Database Schema",
      "path": "postgresql:aria_warehouse",
      "backup_location": "aria_memories/exports/db_schema.sql",
      "priority": "critical",
      "last_verified": null
    },
    {
      "name": "Skill Registry",
      "path": "aria_skills/catalog.py",
      "backup_location": "git_repository",
      "priority": "medium",
      "last_verified": "2026-02-13"
    }
  ],
  "recovery_procedures": {
    "database_restore": "Connect to postgresql container, run init scripts from aria_mind/database/",
    "gateway_restore": "Copy gateway.yaml to workspace, restart openclaw gateway",
    "full_system_restore": "See aria_memories/knowledge/disaster_recovery.md (TODO: create)"
  },
  "verification_status": "manifest_created",
  "next_actions": [
    "Create actual .env backup",
    "Create disaster_recovery.md guide",
    "Set up automated backup cron job"
  ]
}
